pyflowery/__init__.py
pyflowery/exceptions.py
pyflowery/models.py
pyflowery/pyflowery.py
pyflowery/rest_adapter.py
pyflowery/utils.py
pyflowery/version.py
pyflowery-4.0.1.dist-info/METADATA
pyflowery-4.0.1.dist-info/WHEEL
pyflowery-4.0.1.dist-info/licenses/LICENSE
pyflowery-4.0.1.dist-info/RECORD
