Metadata-Version: 2.4
Name: pyflowery
Version: 4.0.1
Summary: A Python API wrapper for the Flowery API
Project-URL: Homepage, https://c.csw.im/cswimr/PyFlowery
Project-URL: Documentation, https://pyflowery.csw.im
Project-URL: Issues, https://c.csw.im/cswimr/PyFlowery/issues
Project-URL: source_archive, https://c.csw.im/cswimr/PyFlowery/archive/5796e759751aa4431e1b21c15c890f71db6fcfa7.tar.gz
License-File: LICENSE
Classifier: Intended Audience :: Developers
Classifier: License :: OSI Approved :: GNU General Public License v3 (GPLv3)
Classifier: Operating System :: OS Independent
Classifier: Programming Language :: Python :: 3.11
Classifier: Programming Language :: Python :: 3.12
Classifier: Programming Language :: Python :: 3.13
Classifier: Programming Language :: Python :: 3.14
Classifier: Topic :: Software Development :: Libraries :: Python Modules
Requires-Python: <4.0,>=3.11
Requires-Dist: aiohttp~=3.13
Requires-Dist: lxml~=6.0
Requires-Dist: pydantic>=2.11.10
Provides-Extra: cli
Requires-Dist: typer~=0.21.1; extra == 'cli'
Provides-Extra: speedups
Requires-Dist: aiohttp[speedups]~=3.13; extra == 'speedups'
Requires-Dist: orjson~=3.11; extra == 'speedups'
